[
  {
    "page": 3,
    "volume": "ナルト30巻",
    "question": "ダンゾウは武闘派",
    "answer": "",
    "note": "問題文のみで答えの行が見当たらない断片。前ページからの継続情報の可能性あり",
    "_reject_reason": "answerが空"
  },
  {
    "page": 3,
    "volume": "ナルト35巻",
    "question": "また千鳥は何変化にはいるか",
    "answer": "",
    "note": "答えの行が次ページに続くと思われるが担当範囲内に見当たらず。判読不明瞭",
    "_reject_reason": "answerが空"
  },
  {
    "page": 4,
    "volume": "ナルト35巻",
    "question": "ペインの正体",
    "answer": "",
    "note": "答え行が見当たらない断片",
    "_reject_reason": "answerが空"
  },
  {
    "page": 5,
    "volume": "ナルト44 45 46 47巻",
    "question": "かむいしゅりけんは何個なげたか",
    "answer": "",
    "note": "答え行が次ページ以降で判読不明瞭",
    "_reject_reason": "answerが空"
  },
  {
    "page": 8,
    "volume": "ナルト55巻",
    "question": "カブトとトビの本拠地を探ろうとしていたメンバーは",
    "answer": "",
    "note": "答えが次ページ以降のため担当範囲では未確認",
    "_reject_reason": "answerが空"
  },
  {
    "page": 11,
    "volume": "ナルト31巻",
    "question": "チヨバアが白秘技　十機近松の集を使ったときに落としたものは",
    "answer": "",
    "note": "答え行が次ページ以降のため担当範囲では未確認",
    "_reject_reason": "answerが空"
  },
  {
    "page": 13,
    "volume": "ナルト50巻",
    "question": "ダンゾウが持つしゃりんがんの数は？",
    "answer": "",
    "note": "答え行が判読不明瞭または欠落",
    "_reject_reason": "answerが空"
  },
  {
    "page": 13,
    "volume": "ナルト52巻",
    "question": "ナルトのしきふういんの鍵を持つがまのなまえは？",
    "answer": "",
    "note": "答えが次ページ以降のため担当範囲では未確認",
    "_reject_reason": "answerが空"
  },
  {
    "page": 14,
    "volume": "ナルト52巻",
    "question": "根性忍伝で主人公を襲った忍びの額当てのマークは？",
    "answer": "?",
    "note": "答えの記号自体が判読不明瞭（クエスチョンマークのみ記載されている可能性）",
    "_reject_reason": "answerが記号のみで信頼できない"
  },
  {
    "page": 18,
    "volume": "ナルト37巻",
    "question": "（見出しのみ、質問文不明）",
    "answer": "ゲロ寅",
    "note": "判読不明瞭。前ページ末尾の性質変化リストに続く固有名詞のみ記載され、対応する質問文が確認できない",
    "_reject_reason": "questionがプレースホルダ/質問文不明"
  },
  {
    "page": 19,
    "volume": null,
    "question": "（右上の追記）〇ネの使う刃の名",
    "answer": "黒澤",
    "note": "手書き追記。質問文冒頭が判読不明瞭",
    "_reject_reason": "noteに信頼性を損なう記載あり: 手書き追記。質問文冒頭が判読不明瞭"
  },
  {
    "page": 19,
    "volume": null,
    "question": "ヒルゼンの父の名は",
    "answer": "サスケ",
    "note": "手書き追記。原文ママだが史実（作中設定）と矛盾するため内容に疑義あり、判読不明瞭ではなく記載内容自体が誤記の可能性",
    "_reject_reason": "noteに信頼性を損なう記載あり: 手書き追記。原文ママだが史実（作中設定）と矛盾するため内容に疑義あり、判読不明瞭ではなく記載内容自体が誤記の可能性"
  },
  {
    "page": 20,
    "volume": null,
    "question": "（前ページからの続き、質問文不明）",
    "answer": "4つ",
    "note": "質問文が前ページに掲載されておらず不明",
    "_reject_reason": "questionがプレースホルダ/質問文不明"
  },
  {
    "page": 22,
    "volume": null,
    "question": "柱間とマダラはそれぞれ幼い頃、戦うときに石を投げ合ったがなんとかいてあったか",
    "answer": "民あり去れ、にげろ／はしうまつマダラ、マダラつはしうま",
    "note": "手書き回答。判読不明瞭",
    "_reject_reason": "noteに信頼性を損なう記載あり: 手書き回答。判読不明瞭"
  },
  {
    "page": 25,
    "volume": "ナルト57・58・59・60巻",
    "question": "サクラに戦争中に告白した人の名前は",
    "answer": "",
    "note": "解答欄がXで消されており記載なし（無回答扱い）",
    "_reject_reason": "answerが空"
  },
  {
    "page": 25,
    "volume": "ナルト57・58・59・60巻",
    "question": "ビーの人柱力の前任者は",
    "answer": "",
    "note": "解答欄がXで消されており記載なし（無回答扱い、前ページの同一質問と重複）",
    "_reject_reason": "answerが空"
  },
  {
    "page": 26,
    "volume": null,
    "question": "（前ページの奇襲部隊等に関する質問の続きと推定、質問文不明）",
    "answer": "アンコ\n日向トクマ\n油目ムタ\nランカ",
    "note": "対応する質問文が前ページ末尾になく不明瞭。人名列のみ判読可能",
    "_reject_reason": "questionがプレースホルダ/質問文不明"
  },
  {
    "page": 27,
    "volume": null,
    "question": "（表紙ページのため設問なし）",
    "answer": "",
    "note": "「第2回 NARUTO検定 上忍 問題用紙」の表紙。全100問、試験時間60分の注意書きのみで、問題・答えの記載はない",
    "_reject_reason": "answerが空"
  },
  {
    "page": 38,
    "volume": null,
    "question": "尾獣の組み合わせとして正しいのは次のうちどれか？",
    "answer": "一尾・守鶴",
    "note": "選択肢①一尾・重明 ②五尾・又旅 ③六尾・犀犬 ④七尾・九喇嘛。丸印の位置が判読不明瞭。選択肢の記載自体に一部誤記の可能性あり",
    "readability": "判読不明瞭",
    "_reject_reason": "noteに信頼性を損なう記載あり: 選択肢①一尾・重明 ②五尾・又旅 ③六尾・犀犬 ④七尾・九喇嘛。丸印の位置が判読不明瞭。選択肢の記載自体に一部誤記の可能性あり"
  },
  {
    "page": 39,
    "volume": null,
    "question": "穢土転生を解くための、最後の印はどれか？",
    "answer": "判読不明瞭",
    "note": "選択肢①子 ②卯 ③辰 ④亥。複数箇所に丸・二重丸があり正解の特定が判読不明瞭",
    "_reject_reason": "answerが判読不明瞭"
  },
  {
    "page": 47,
    "volume": null,
    "question": "チヨバアが言う写輪眼を持つ者との戦い方で、「一対一なら必ず逃げろ」の後に続く台詞は次の内どれか?\n①二対一でも必ず逃げろ\n②二対一なら一人は逃げろ\n③二対一なら幻術を解け\n④二対一なら後ろを取れ",
    "answer": "",
    "note": "正解の丸印なし/判読不明瞭",
    "_reject_reason": "answerが空"
  },
  {
    "page": 47,
    "volume": null,
    "question": "中忍選抜試験、第二試験でサクラを襲った音忍三人組に含まれないのは?\n①ザク\n②ダン\n③ドス\n④キン",
    "answer": "",
    "note": "正解の丸印なし/判読不明瞭",
    "_reject_reason": "answerが空"
  },
  {
    "page": 47,
    "volume": null,
    "question": "油女一族が自身の身体に寄生させ、自在に操ることができる蟲を何という?\n①寄壊蟲\n②寄生蟲\n③寄爆蟲\n④寄倒蟲",
    "answer": "",
    "note": "正解の丸印なし/判読不明瞭",
    "_reject_reason": "answerが空"
  },
  {
    "page": 47,
    "volume": null,
    "question": "中忍選抜試験、第三試験予選の第四回戦は誰と誰の対戦だったか?\n①うずまきナルトVS犬塚キバ\n②テンテンVSテマリ\n③春野サクラVS山中いの\n④我愛羅VSロック・リー",
    "answer": "",
    "note": "正解の丸印なし/判読不明瞭",
    "_reject_reason": "answerが空"
  },
  {
    "page": 47,
    "volume": null,
    "question": "チャクラの通り道である経絡系上にあるツボ、「点穴」は通常何個あるか?\n①365個\n②35個\n③3600個\n④361個",
    "answer": "",
    "note": "正解の丸印なし/判読不明瞭。チェックマークのみで選択肢に丸印なし",
    "_reject_reason": "answerが空"
  },
  {
    "page": 48,
    "volume": null,
    "question": "大蛇丸の穢土転生の術により蘇生された初代火影が三代目火影・猿飛ヒルゼンに対して使った、彼のみが使える秘術はどれか?\n①樹界降誕\n②大樹林の術\n③土流壁\n④水龍弾",
    "answer": "",
    "note": "正解の丸印なし/判読不明瞭",
    "_reject_reason": "answerが空"
  },
  {
    "page": 49,
    "volume": null,
    "question": "口寄せの術の印はどれか?\n①子・丑・寅・卯・辰\n②寅・卯・辰・巳・午\n③巳・午・未・申・酉\n④亥・戌・酉・申・未",
    "answer": "",
    "note": "正解の丸印なし/判読不明瞭",
    "_reject_reason": "answerが空"
  },
  {
    "page": 49,
    "volume": null,
    "question": "木ノ葉の特別上忍、月光ハヤテを殺害したのは誰か?\n①バキ\n②ボキ\n③ヘキ\n④ジン",
    "answer": "",
    "note": "正解の丸印なし/判読不明瞭",
    "_reject_reason": "answerが空"
  },
  {
    "page": 49,
    "volume": null,
    "question": "伝説の三忍、綱手の恋人と弟の名前で正しい組み合わせはどれか?\n①恋人:ダン 弟:縄樹\n②恋人:タツ 弟:縄太\n③恋人:ダク 弟:縄吉\n④恋人:タキ 弟:縄満",
    "answer": "",
    "note": "正解の丸印なし/判読不明瞭",
    "_reject_reason": "answerが空"
  },
  {
    "page": 50,
    "volume": null,
    "question": "アスマ班でシカマルの中忍昇格祝いをした店の名前は?\n①焼肉Q\n②焼肉R\n③焼肉A\n④焼肉E",
    "answer": "",
    "note": "正解の丸印なし/判読不明瞭",
    "_reject_reason": "answerが空"
  },
  {
    "page": 51,
    "volume": null,
    "question": "中忍選抜試験、第三試験予選でカンクロウと戦ったのは?\n①テマリ\n②ザク・アブミ\n③剣・ミスミ\n④薬師カブト",
    "answer": "",
    "note": "正解の丸印なし/判読不明瞭",
    "_reject_reason": "answerが空"
  },
  {
    "page": 51,
    "volume": null,
    "question": "木ノ葉崩し始動と共に、音の忍が三代目火影を閉じ込めるときに使った術は?\n①氷火絶陣\n②四紫炎陣\n③四死炎陣\n④四鬼炎陣",
    "answer": "",
    "note": "正解の丸印なし/判読不明瞭",
    "_reject_reason": "answerが空"
  },
  {
    "page": 51,
    "volume": null,
    "question": "ナルトがアカデミーを卒業したときの卒業生は何名?\n①24名\n②25名\n③27名\n④30名",
    "answer": "",
    "note": "正解の丸印なし/判読不明瞭",
    "_reject_reason": "answerが空"
  },
  {
    "page": 52,
    "volume": null,
    "question": "大蛇丸の呪印の力を無理やり「状態2」に覚醒させる薬を何という?\n①覚心丸\n②醒心丸\n③心開丸\n④増血丸",
    "answer": "",
    "note": "正解の丸印なし/判読不明瞭",
    "_reject_reason": "answerが空"
  },
  {
    "page": 52,
    "volume": null,
    "question": "ネジが鬼童丸との戦闘で、チャクラで作った矢に打ち抜かれた箇所はどこか?\n①右肩と左脇腹\n②左肩と右脇腹\n③右ふくらはぎと左腕\n④左ふくらはぎと右腕",
    "answer": "",
    "note": "正解の丸印なし/判読不明瞭",
    "_reject_reason": "answerが空"
  },
  {
    "page": 52,
    "volume": null,
    "question": "多由也がシカマルとの戦闘で呪印状態2になったのはいつか?\n①影真似の術にかかった時\n②口寄せした三体の怪物が影真似の術にかけられた時\n③シカマルと一対一の戦闘が始まってすぐ\n④笛が折られた時",
    "answer": "",
    "note": "正解の丸印なし/判読不明瞭",
    "_reject_reason": "answerが空"
  },
  {
    "page": 53,
    "volume": null,
    "question": "犬塚キバと赤丸の人獣混合変化でできるのは何か?\n①ケルベロス\n②双頭犬\n③双頭狼\n④黒丸",
    "answer": "",
    "note": "正解の丸印なし/判読不明瞭",
    "_reject_reason": "answerが空"
  },
  {
    "page": 53,
    "volume": null,
    "question": "かぐや一族が一族だけで戦いを挑んだ里はどこか?\n①木ノ葉隠れの里\n②砂隠れの里\n③霧隠れの里\n④霧隠れの里",
    "answer": "③霧隠れの里",
    "note": "選択肢③と④が印刷上どちらも「霧隠れの里」に見える。判読不明瞭の可能性あり",
    "_reject_reason": "noteに信頼性を損なう記載あり: 選択肢③と④が印刷上どちらも「霧隠れの里」に見える。判読不明瞭の可能性あり"
  },
  {
    "page": 57,
    "volume": null,
    "question": "螺旋丸に関する記述で正しいのは次のうちどれか?\n①亥の印を結ぶ\n②会得難易度はSランク\n③修業の第一段階でゴムボールを使う\n④四代目火影が遺した忍術である",
    "answer": "",
    "note": "正解の丸印なし/判読不明瞭",
    "_reject_reason": "answerが空"
  },
  {
    "page": 59,
    "volume": null,
    "question": "問060 再不斬との戦いで、カカシが写輪眼を使い、術をかけようとした再不斬本人より先に繰り出した術は？ ①水遁・大瀑布の術 ②水遁・水龍弾の術 ③水牢の術 ④水遁・水陣壁の術",
    "answer": "",
    "note": "判読不明瞭（丸印を確認できず）",
    "_reject_reason": "answerが空"
  },
  {
    "page": 62,
    "volume": null,
    "question": "問079 中忍選抜試験、第二試験でナルトたちはバラバラになった時の合言葉を決めた。「大勢の敵の騒ぎは忍びよし○○に隠れ家もなし・・・・」○○に入る言葉は何か？ ①騒がしい方 ②静かな方 ③北方 ④南方",
    "answer": "",
    "note": "判読不明瞭（丸印を確認できず）",
    "_reject_reason": "answerが空"
  },
  {
    "page": 64,
    "volume": null,
    "question": "問088 再不斬が死の間際にカカシに頼んだことは？ ①白の隣に埋葬してほしい ②敵を討ってほしい ③白の顔が見たい ④とどめをさしてほしい",
    "answer": "",
    "note": "判読不明瞭（丸印を確認できず）",
    "_reject_reason": "answerが空"
  },
  {
    "page": 64,
    "volume": null,
    "question": "問090 三代目火影・猿飛ヒルゼンの最期の台詞は？ ①火の意志は絶えぬ ②共に逝けぬのが残念じゃ… ③また木の葉は芽吹く ④木ノ葉の里はわしの家じゃ",
    "answer": "",
    "note": "判読不明瞭（丸印を確認できず）",
    "_reject_reason": "answerが空"
  },
  {
    "page": 67,
    "volume": null,
    "question": "問007 サスケの嫌いな食べ物は次のうちどれか？ ①トマト ②おかかおにぎり ③納豆 ④豆腐",
    "answer": "",
    "note": "判読不明瞭（丸印を確認できず）",
    "_reject_reason": "answerが空"
  },
  {
    "page": 68,
    "volume": null,
    "question": "問013 アカデミー時代、ナルトの最も苦手な忍術だったのは何か？ ①おいろけの術 ②飛雷神の術 ③変化の術 ④分身の術",
    "answer": "",
    "note": "判読不明瞭（丸印を確認できず）",
    "_reject_reason": "answerが空"
  },
  {
    "page": 68,
    "volume": null,
    "question": "問015 夕日紅率いる第八班でないのは次のうち誰か？ ①日向ヒナタ ②日向ネジ ③油女シノ ④犬塚キバ",
    "answer": "",
    "note": "判読不明瞭（丸印を確認できず）",
    "_reject_reason": "answerが空"
  },
  {
    "page": 70,
    "volume": null,
    "question": "問023 サスケ奪還作戦のために、優秀と思う下忍を集めろと言われた奈良シカマルが、唯一自分から誘った人物は誰か？ ①犬塚キバ ②秋道チョウジ ③日向ネジ ④油女シノ",
    "answer": "",
    "note": "判読不明瞭（丸印を確認できず）",
    "_reject_reason": "answerが空"
  },
  {
    "page": 70,
    "volume": null,
    "question": "問024 \"千鳥\"の名前の由来で正しいのは次の内どれか？ ①千羽の鳥が羽ばたいたような音が出るから ②鳥の鳴き声のような攻撃音が出るから ③鳥のように飛んで攻撃するから ④チャクラが翼のような形になるから",
    "answer": "",
    "note": "判読不明瞭（丸印を確認できず）",
    "_reject_reason": "answerが空"
  }
]